{
    "maps": [
        {
            "title": "Methane at 400 hPa",
            "type": "continuous",
            "legend": {
                "tooltips": [
                    "< 1600.0",
                    "1600.0 - 1602.0",
                    "1602.0 - 1604.0",
                    "1604.0 - 1606.0",
                    "1606.0 - 1608.0",
                    "1608.0 - 1610.0",
                    "1610.0 - 1612.0",
                    "1612.0 - 1614.0",
                    "1614.0 - 1616.0",
                    "1616.0 - 1618.0",
                    "1618.0 - 1620.0",
                    "1620.0 - 1622.0",
                    "1622.0 - 1624.0",
                    "1624.0 - 1626.0",
                    "1626.0 - 1628.0",
                    "1628.0 - 1630.0",
                    "1630.0 - 1632.0",
                    "1632.0 - 1634.0",
                    "1634.0 - 1636.0",
                    "1636.0 - 1638.0",
                    "1638.0 - 1640.0",
                    "1640.0 - 1642.0",
                    "1642.0 - 1644.0",
                    "1644.0 - 1646.0",
                    "1646.0 - 1648.0",
                    "1648.0 - 1650.0",
                    "1650.0 - 1652.0",
                    "1652.0 - 1654.0",
                    "1654.0 - 1656.0",
                    "1656.0 - 1658.0",
                    "1658.0 - 1660.0",
                    "1660.0 - 1662.0",
                    "1662.0 - 1664.0",
                    "1664.0 - 1666.0",
                    "1666.0 - 1668.0",
                    "1668.0 - 1670.0",
                    "1670.0 - 1672.0",
                    "1672.0 - 1674.0",
                    "1674.0 - 1676.0",
                    "1676.0 - 1678.0",
                    "1678.0 - 1680.0",
                    "1680.0 - 1682.0",
                    "1682.0 - 1684.0",
                    "1684.0 - 1686.0",
                    "1686.0 - 1688.0",
                    "1688.0 - 1690.0",
                    "1690.0 - 1692.0",
                    "1692.0 - 1694.0",
                    "1694.0 - 1696.0",
                    "1696.0 - 1698.0",
                    "1698.0 - 1700.0",
                    "1700.0 - 1702.0",
                    "1702.0 - 1704.0",
                    "1704.0 - 1706.0",
                    "1706.0 - 1708.0",
                    "1708.0 - 1710.0",
                    "1710.0 - 1712.0",
                    "1712.0 - 1714.0",
                    "1714.0 - 1716.0",
                    "1716.0 - 1718.0",
                    "1718.0 - 1720.0",
                    "1720.0 - 1722.0",
                    "1722.0 - 1724.0",
                    "1724.0 - 1726.0",
                    "1726.0 - 1728.0",
                    "1728.0 - 1730.0",
                    "1730.0 - 1732.0",
                    "1732.0 - 1734.0",
                    "1734.0 - 1736.0",
                    "1736.0 - 1738.0",
                    "1738.0 - 1740.0",
                    "1740.0 - 1742.0",
                    "1742.0 - 1744.0",
                    "1744.0 - 1746.0",
                    "1746.0 - 1748.0",
                    "1748.0 - 1750.0",
                    "1750.0 - 1752.0",
                    "1752.0 - 1754.0",
                    "1754.0 - 1756.0",
                    "1756.0 - 1758.0",
                    "1758.0 - 1760.0",
                    "1760.0 - 1762.0",
                    "1762.0 - 1764.0",
                    "1764.0 - 1766.0",
                    "1766.0 - 1768.0",
                    "1768.0 - 1770.0",
                    "1770.0 - 1772.0",
                    "1772.0 - 1774.0",
                    "1774.0 - 1776.0",
                    "1776.0 - 1778.0",
                    "1778.0 - 1780.0",
                    "1780.0 - 1782.0",
                    "1782.0 - 1784.0",
                    "1784.0 - 1786.0",
                    "1786.0 - 1788.0",
                    "1788.0 - 1790.0",
                    "1790.0 - 1792.0",
                    "1792.0 - 1794.0",
                    "1794.0 - 1796.0",
                    "1796.0 - 1798.0",
                    "1798.0 - 1800.0",
                    "1800.0 - 1802.0",
                    "1802.0 - 1804.0",
                    "1804.0 - 1806.0",
                    "1806.0 - 1808.0",
                    "1808.0 - 1810.0",
                    "1810.0 - 1812.0",
                    "1812.0 - 1814.0",
                    "1814.0 - 1816.0",
                    "1816.0 - 1818.0",
                    "1818.0 - 1820.0",
                    "1820.0 - 1822.0",
                    "1822.0 - 1824.0",
                    "1824.0 - 1826.0",
                    "1826.0 - 1828.0",
                    "1828.0 - 1830.0",
                    "1830.0 - 1832.0",
                    "1832.0 - 1834.0",
                    "1834.0 - 1836.0",
                    "1836.0 - 1838.0",
                    "1838.0 - 1840.0",
                    "1840.0 - 1842.0",
                    "1842.0 - 1844.0",
                    "1844.0 - 1846.0",
                    "1846.0 - 1848.0",
                    "1848.0 - 1850.0",
                    "1850.0 - 1852.0",
                    "1852.0 - 1854.0",
                    "1854.0 - 1856.0",
                    "1856.0 - 1858.0",
                    "1858.0 - 1860.0",
                    "1860.0 - 1862.0",
                    "1862.0 - 1864.0",
                    "1864.0 - 1866.0",
                    "1866.0 - 1868.0",
                    "1868.0 - 1870.0",
                    "1870.0 - 1872.0",
                    "1872.0 - 1874.0",
                    "1874.0 - 1876.0",
                    "1876.0 - 1878.0",
                    "1878.0 - 1880.0",
                    "1880.0 - 1882.0",
                    "1882.0 - 1884.0",
                    "1884.0 - 1886.0",
                    "1886.0 - 1888.0",
                    "1888.0 - 1890.0",
                    "1890.0 - 1892.0",
                    "1892.0 - 1894.0",
                    "1894.0 - 1896.0",
                    "1896.0 - 1898.0",
                    "1898.0 - 1900.0",
                    "1900.0 - 1902.0",
                    "1902.0 - 1904.0",
                    "1904.0 - 1906.0",
                    "1906.0 - 1908.0",
                    "1908.0 - 1910.0",
                    "1910.0 - 1912.0",
                    "1912.0 - 1914.0",
                    "1914.0 - 1916.0",
                    "1916.0 - 1918.0",
                    "1918.0 - 1920.0",
                    "1920.0 - 1922.0",
                    "1922.0 - 1924.0",
                    "1924.0 - 1926.0",
                    "1926.0 - 1928.0",
                    "1928.0 - 1930.0",
                    "1930.0 - 1932.0",
                    "1932.0 - 1934.0",
                    "1934.0 - 1936.0",
                    "1936.0 - 1938.0",
                    "1938.0 - 1940.0",
                    "1940.0 - 1942.0",
                    "1942.0 - 1944.0",
                    "1944.0 - 1946.0",
                    "1946.0 - 1948.0",
                    "1948.0 - 1950.0",
                    "1950.0 - 1952.0",
                    "1952.0 - 1954.0",
                    "1954.0 - 1956.0",
                    "1956.0 - 1958.0",
                    "1958.0 - 1960.0",
                    "1960.0 - 1962.0",
                    "1962.0 - 1964.0",
                    "1964.0 - 1966.0",
                    "1966.0 - 1968.0",
                    "1968.0 - 1970.0",
                    "1970.0 - 1972.0",
                    "1972.0 - 1974.0",
                    "1974.0 - 1976.0",
                    "1976.0 - 1978.0",
                    "1978.0 - 1980.0",
                    "1980.0 - 1982.0",
                    "1982.0 - 1984.0",
                    "1984.0 - 1986.0",
                    "1986.0 - 1988.0",
                    "1988.0 - 1990.0",
                    "1990.0 - 1992.0",
                    "1992.0 - 1994.0",
                    "1994.0 - 1996.0",
                    "1996.0 - 1998.0",
                    "1998.0 - 2000.0",
                    ">= 2000.0"
                ],
                "title": "Methane at 400 hPa",
                "colors": [
                    "f2f3f6ff",
                    "e4e4d2ff",
                    "e3e5d2ff",
                    "e2e5d2ff",
                    "e2e5d1ff",
                    "e1e5d0ff",
                    "e0e6d0ff",
                    "dfe6d0ff",
                    "dee5cfff",
                    "dde6cfff",
                    "dbe6ceff",
                    "dae6ceff",
                    "d9e6ceff",
                    "d8e6cdff",
                    "d6e6cdff",
                    "d5e7ccff",
                    "d4e6ccff",
                    "d2e7cbff",
                    "d1e7caff",
                    "cfe7caff",
                    "cee7c9ff",
                    "cce7c9ff",
                    "cbe7c8ff",
                    "c9e8c8ff",
                    "c8e8c7ff",
                    "c6e8c6ff",
                    "c5e8c5ff",
                    "c4e8c5ff",
                    "c2e8c4ff",
                    "c1e8c3ff",
                    "bfe8c2ff",
                    "bee9c1ff",
                    "bde9c0ff",
                    "bce9bfff",
                    "bbe9beff",
                    "bae8bdff",
                    "b9e8bbff",
                    "b8e8baff",
                    "b7e7b9ff",
                    "b6e7b7ff",
                    "b5e6b6ff",
                    "b4e6b4ff",
                    "b4e5b3ff",
                    "b3e5b1ff",
                    "b2e5afff",
                    "b1e4aeff",
                    "b0e4acff",
                    "b0e3aaff",
                    "afe3a8ff",
                    "aee2a6ff",
                    "ade1a4ff",
                    "ade1a2ff",
                    "ace0a0ff",
                    "abdf9dff",
                    "aadf9bff",
                    "aade99ff",
                    "a9dd97ff",
                    "a9dc95ff",
                    "a8dc92ff",
                    "a8db90ff",
                    "a7da8eff",
                    "a7d98bff",
                    "a6d889ff",
                    "a6d787ff",
                    "a6d684ff",
                    "a6d582ff",
                    "a5d480ff",
                    "a5d37eff",
                    "a5d27cff",
                    "a6d17aff",
                    "a6d078ff",
                    "a6cf76ff",
                    "a6cd74ff",
                    "a6cc73ff",
                    "a6cb71ff",
                    "a6ca6fff",
                    "a7c96dff",
                    "a7c86cff",
                    "a7c66bff",
                    "a8c569ff",
                    "a8c368ff",
                    "a9c266ff",
                    "aac065ff",
                    "abbf64ff",
                    "acbd62ff",
                    "adbc61ff",
                    "afba5fff",
                    "b0b85eff",
                    "b2b75dff",
                    "b3b55cff",
                    "b5b35aff",
                    "b6b159ff",
                    "b8b058ff",
                    "b9ae57ff",
                    "bbac56ff",
                    "bdaa55ff",
                    "bea954ff",
                    "c0a753ff",
                    "c1a552ff",
                    "c3a351ff",
                    "c5a150ff",
                    "c79f4fff",
                    "c99d4eff",
                    "cb9b4dff",
                    "cc994cff",
                    "ce974cff",
                    "d0954bff",
                    "d1934aff",
                    "d39249ff",
                    "d49049ff",
                    "d68e48ff",
                    "d78d48ff",
                    "d88b47ff",
                    "da8947ff",
                    "db8846ff",
                    "dc8646ff",
                    "dd8446ff",
                    "dd8346ff",
                    "de8145ff",
                    "de7f46ff",
                    "df7d46ff",
                    "df7c45ff",
                    "df7a45ff",
                    "df7846ff",
                    "df7746ff",
                    "df7546ff",
                    "e07446ff",
                    "e07246ff",
                    "e07146ff",
                    "e06f47ff",
                    "e06e47ff",
                    "e06c47ff",
                    "e06b48ff",
                    "e06949ff",
                    "e16849ff",
                    "e1664aff",
                    "e1654bff",
                    "e1634cff",
                    "e1624cff",
                    "e1614dff",
                    "e15f4eff",
                    "e15e4eff",
                    "e25d4fff",
                    "e15b4fff",
                    "e15a50ff",
                    "e25850ff",
                    "e25750ff",
                    "e25651ff",
                    "e25451ff",
                    "e25351ff",
                    "e15150ff",
                    "e15050ff",
                    "e04f50ff",
                    "de4d50ff",
                    "dd4c4fff",
                    "db4a4eff",
                    "d8494eff",
                    "d6474dff",
                    "d4464cff",
                    "d1444bff",
                    "cf434aff",
                    "cc4149ff",
                    "c93f48ff",
                    "c63e47ff",
                    "c33c46ff",
                    "c03b45ff",
                    "bd3943ff",
                    "ba3842ff",
                    "b73641ff",
                    "b43540ff",
                    "b0343fff",
                    "ad323eff",
                    "aa313dff",
                    "a7303cff",
                    "a42e3bff",
                    "a12d39ff",
                    "9e2c38ff",
                    "9b2b38ff",
                    "992a37ff",
                    "962936ff",
                    "932835ff",
                    "912735ff",
                    "8e2635ff",
                    "8b2635ff",
                    "882534ff",
                    "842434ff",
                    "812334ff",
                    "7e2335ff",
                    "7b2334ff",
                    "782334ff",
                    "752235ff",
                    "722235ff",
                    "702235ff",
                    "6d2335ff",
                    "6a2335ff",
                    "682335ff",
                    "662335ff",
                    "642335ff",
                    "622336ff",
                    "602335ff",
                    "5e2436ff",
                    "3e0015ff"
                ],
                "maxLabel": ">= 2000.0",
                "minLabel": "< 1600.0",
                "units": "ppbv",
                "type": "continuous",
                "id": "AIRS_Methane_Volume_Mixing_Ratio_Daily_Night_0_legend"
            },
            "entries": {
                "values": [
                    [
                        2.2250738585072014e-308,
                        1600.0
                    ],
                    [
                        1600.0,
                        1602.0
                    ],
                    [
                        1602.0,
                        1604.0
                    ],
                    [
                        1604.0,
                        1606.0
                    ],
                    [
                        1606.0,
                        1608.0
                    ],
                    [
                        1608.0,
                        1610.0
                    ],
                    [
                        1610.0,
                        1612.0
                    ],
                    [
                        1612.0,
                        1614.0
                    ],
                    [
                        1614.0,
                        1616.0
                    ],
                    [
                        1616.0,
                        1618.0
                    ],
                    [
                        1618.0,
                        1620.0
                    ],
                    [
                        1620.0,
                        1622.0
                    ],
                    [
                        1622.0,
                        1624.0
                    ],
                    [
                        1624.0,
                        1626.0
                    ],
                    [
                        1626.0,
                        1628.0
                    ],
                    [
                        1628.0,
                        1630.0
                    ],
                    [
                        1630.0,
                        1632.0
                    ],
                    [
                        1632.0,
                        1634.0
                    ],
                    [
                        1634.0,
                        1636.0
                    ],
                    [
                        1636.0,
                        1638.0
                    ],
                    [
                        1638.0,
                        1640.0
                    ],
                    [
                        1640.0,
                        1642.0
                    ],
                    [
                        1642.0,
                        1644.0
                    ],
                    [
                        1644.0,
                        1646.0
                    ],
                    [
                        1646.0,
                        1648.0
                    ],
                    [
                        1648.0,
                        1650.0
                    ],
                    [
                        1650.0,
                        1652.0
                    ],
                    [
                        1652.0,
                        1654.0
                    ],
                    [
                        1654.0,
                        1656.0
                    ],
                    [
                        1656.0,
                        1658.0
                    ],
                    [
                        1658.0,
                        1660.0
                    ],
                    [
                        1660.0,
                        1662.0
                    ],
                    [
                        1662.0,
                        1664.0
                    ],
                    [
                        1664.0,
                        1666.0
                    ],
                    [
                        1666.0,
                        1668.0
                    ],
                    [
                        1668.0,
                        1670.0
                    ],
                    [
                        1670.0,
                        1672.0
                    ],
                    [
                        1672.0,
                        1674.0
                    ],
                    [
                        1674.0,
                        1676.0
                    ],
                    [
                        1676.0,
                        1678.0
                    ],
                    [
                        1678.0,
                        1680.0
                    ],
                    [
                        1680.0,
                        1682.0
                    ],
                    [
                        1682.0,
                        1684.0
                    ],
                    [
                        1684.0,
                        1686.0
                    ],
                    [
                        1686.0,
                        1688.0
                    ],
                    [
                        1688.0,
                        1690.0
                    ],
                    [
                        1690.0,
                        1692.0
                    ],
                    [
                        1692.0,
                        1694.0
                    ],
                    [
                        1694.0,
                        1696.0
                    ],
                    [
                        1696.0,
                        1698.0
                    ],
                    [
                        1698.0,
                        1700.0
                    ],
                    [
                        1700.0,
                        1702.0
                    ],
                    [
                        1702.0,
                        1704.0
                    ],
                    [
                        1704.0,
                        1706.0
                    ],
                    [
                        1706.0,
                        1708.0
                    ],
                    [
                        1708.0,
                        1710.0
                    ],
                    [
                        1710.0,
                        1712.0
                    ],
                    [
                        1712.0,
                        1714.0
                    ],
                    [
                        1714.0,
                        1716.0
                    ],
                    [
                        1716.0,
                        1718.0
                    ],
                    [
                        1718.0,
                        1720.0
                    ],
                    [
                        1720.0,
                        1722.0
                    ],
                    [
                        1722.0,
                        1724.0
                    ],
                    [
                        1724.0,
                        1726.0
                    ],
                    [
                        1726.0,
                        1728.0
                    ],
                    [
                        1728.0,
                        1730.0
                    ],
                    [
                        1730.0,
                        1732.0
                    ],
                    [
                        1732.0,
                        1734.0
                    ],
                    [
                        1734.0,
                        1736.0
                    ],
                    [
                        1736.0,
                        1738.0
                    ],
                    [
                        1738.0,
                        1740.0
                    ],
                    [
                        1740.0,
                        1742.0
                    ],
                    [
                        1742.0,
                        1744.0
                    ],
                    [
                        1744.0,
                        1746.0
                    ],
                    [
                        1746.0,
                        1748.0
                    ],
                    [
                        1748.0,
                        1750.0
                    ],
                    [
                        1750.0,
                        1752.0
                    ],
                    [
                        1752.0,
                        1754.0
                    ],
                    [
                        1754.0,
                        1756.0
                    ],
                    [
                        1756.0,
                        1758.0
                    ],
                    [
                        1758.0,
                        1760.0
                    ],
                    [
                        1760.0,
                        1762.0
                    ],
                    [
                        1762.0,
                        1764.0
                    ],
                    [
                        1764.0,
                        1766.0
                    ],
                    [
                        1766.0,
                        1768.0
                    ],
                    [
                        1768.0,
                        1770.0
                    ],
                    [
                        1770.0,
                        1772.0
                    ],
                    [
                        1772.0,
                        1774.0
                    ],
                    [
                        1774.0,
                        1776.0
                    ],
                    [
                        1776.0,
                        1778.0
                    ],
                    [
                        1778.0,
                        1780.0
                    ],
                    [
                        1780.0,
                        1782.0
                    ],
                    [
                        1782.0,
                        1784.0
                    ],
                    [
                        1784.0,
                        1786.0
                    ],
                    [
                        1786.0,
                        1788.0
                    ],
                    [
                        1788.0,
                        1790.0
                    ],
                    [
                        1790.0,
                        1792.0
                    ],
                    [
                        1792.0,
                        1794.0
                    ],
                    [
                        1794.0,
                        1796.0
                    ],
                    [
                        1796.0,
                        1798.0
                    ],
                    [
                        1798.0,
                        1800.0
                    ],
                    [
                        1800.0,
                        1802.0
                    ],
                    [
                        1802.0,
                        1804.0
                    ],
                    [
                        1804.0,
                        1806.0
                    ],
                    [
                        1806.0,
                        1808.0
                    ],
                    [
                        1808.0,
                        1810.0
                    ],
                    [
                        1810.0,
                        1812.0
                    ],
                    [
                        1812.0,
                        1814.0
                    ],
                    [
                        1814.0,
                        1816.0
                    ],
                    [
                        1816.0,
                        1818.0
                    ],
                    [
                        1818.0,
                        1820.0
                    ],
                    [
                        1820.0,
                        1822.0
                    ],
                    [
                        1822.0,
                        1824.0
                    ],
                    [
                        1824.0,
                        1826.0
                    ],
                    [
                        1826.0,
                        1828.0
                    ],
                    [
                        1828.0,
                        1830.0
                    ],
                    [
                        1830.0,
                        1832.0
                    ],
                    [
                        1832.0,
                        1834.0
                    ],
                    [
                        1834.0,
                        1836.0
                    ],
                    [
                        1836.0,
                        1838.0
                    ],
                    [
                        1838.0,
                        1840.0
                    ],
                    [
                        1840.0,
                        1842.0
                    ],
                    [
                        1842.0,
                        1844.0
                    ],
                    [
                        1844.0,
                        1846.0
                    ],
                    [
                        1846.0,
                        1848.0
                    ],
                    [
                        1848.0,
                        1850.0
                    ],
                    [
                        1850.0,
                        1852.0
                    ],
                    [
                        1852.0,
                        1854.0
                    ],
                    [
                        1854.0,
                        1856.0
                    ],
                    [
                        1856.0,
                        1858.0
                    ],
                    [
                        1858.0,
                        1860.0
                    ],
                    [
                        1860.0,
                        1862.0
                    ],
                    [
                        1862.0,
                        1864.0
                    ],
                    [
                        1864.0,
                        1866.0
                    ],
                    [
                        1866.0,
                        1868.0
                    ],
                    [
                        1868.0,
                        1870.0
                    ],
                    [
                        1870.0,
                        1872.0
                    ],
                    [
                        1872.0,
                        1874.0
                    ],
                    [
                        1874.0,
                        1876.0
                    ],
                    [
                        1876.0,
                        1878.0
                    ],
                    [
                        1878.0,
                        1880.0
                    ],
                    [
                        1880.0,
                        1882.0
                    ],
                    [
                        1882.0,
                        1884.0
                    ],
                    [
                        1884.0,
                        1886.0
                    ],
                    [
                        1886.0,
                        1888.0
                    ],
                    [
                        1888.0,
                        1890.0
                    ],
                    [
                        1890.0,
                        1892.0
                    ],
                    [
                        1892.0,
                        1894.0
                    ],
                    [
                        1894.0,
                        1896.0
                    ],
                    [
                        1896.0,
                        1898.0
                    ],
                    [
                        1898.0,
                        1900.0
                    ],
                    [
                        1900.0,
                        1902.0
                    ],
                    [
                        1902.0,
                        1904.0
                    ],
                    [
                        1904.0,
                        1906.0
                    ],
                    [
                        1906.0,
                        1908.0
                    ],
                    [
                        1908.0,
                        1910.0
                    ],
                    [
                        1910.0,
                        1912.0
                    ],
                    [
                        1912.0,
                        1914.0
                    ],
                    [
                        1914.0,
                        1916.0
                    ],
                    [
                        1916.0,
                        1918.0
                    ],
                    [
                        1918.0,
                        1920.0
                    ],
                    [
                        1920.0,
                        1922.0
                    ],
                    [
                        1922.0,
                        1924.0
                    ],
                    [
                        1924.0,
                        1926.0
                    ],
                    [
                        1926.0,
                        1928.0
                    ],
                    [
                        1928.0,
                        1930.0
                    ],
                    [
                        1930.0,
                        1932.0
                    ],
                    [
                        1932.0,
                        1934.0
                    ],
                    [
                        1934.0,
                        1936.0
                    ],
                    [
                        1936.0,
                        1938.0
                    ],
                    [
                        1938.0,
                        1940.0
                    ],
                    [
                        1940.0,
                        1942.0
                    ],
                    [
                        1942.0,
                        1944.0
                    ],
                    [
                        1944.0,
                        1946.0
                    ],
                    [
                        1946.0,
                        1948.0
                    ],
                    [
                        1948.0,
                        1950.0
                    ],
                    [
                        1950.0,
                        1952.0
                    ],
                    [
                        1952.0,
                        1954.0
                    ],
                    [
                        1954.0,
                        1956.0
                    ],
                    [
                        1956.0,
                        1958.0
                    ],
                    [
                        1958.0,
                        1960.0
                    ],
                    [
                        1960.0,
                        1962.0
                    ],
                    [
                        1962.0,
                        1964.0
                    ],
                    [
                        1964.0,
                        1966.0
                    ],
                    [
                        1966.0,
                        1968.0
                    ],
                    [
                        1968.0,
                        1970.0
                    ],
                    [
                        1970.0,
                        1972.0
                    ],
                    [
                        1972.0,
                        1974.0
                    ],
                    [
                        1974.0,
                        1976.0
                    ],
                    [
                        1976.0,
                        1978.0
                    ],
                    [
                        1978.0,
                        1980.0
                    ],
                    [
                        1980.0,
                        1982.0
                    ],
                    [
                        1982.0,
                        1984.0
                    ],
                    [
                        1984.0,
                        1986.0
                    ],
                    [
                        1986.0,
                        1988.0
                    ],
                    [
                        1988.0,
                        1990.0
                    ],
                    [
                        1990.0,
                        1992.0
                    ],
                    [
                        1992.0,
                        1994.0
                    ],
                    [
                        1994.0,
                        1996.0
                    ],
                    [
                        1996.0,
                        1998.0
                    ],
                    [
                        1998.0,
                        2000.0
                    ],
                    [
                        2000.0,
                        1.7976931348623157e+308
                    ]
                ],
                "colors": [
                    "f2f3f6ff",
                    "e4e4d2ff",
                    "e3e5d2ff",
                    "e2e5d2ff",
                    "e2e5d1ff",
                    "e1e5d0ff",
                    "e0e6d0ff",
                    "dfe6d0ff",
                    "dee5cfff",
                    "dde6cfff",
                    "dbe6ceff",
                    "dae6ceff",
                    "d9e6ceff",
                    "d8e6cdff",
                    "d6e6cdff",
                    "d5e7ccff",
                    "d4e6ccff",
                    "d2e7cbff",
                    "d1e7caff",
                    "cfe7caff",
                    "cee7c9ff",
                    "cce7c9ff",
                    "cbe7c8ff",
                    "c9e8c8ff",
                    "c8e8c7ff",
                    "c6e8c6ff",
                    "c5e8c5ff",
                    "c4e8c5ff",
                    "c2e8c4ff",
                    "c1e8c3ff",
                    "bfe8c2ff",
                    "bee9c1ff",
                    "bde9c0ff",
                    "bce9bfff",
                    "bbe9beff",
                    "bae8bdff",
                    "b9e8bbff",
                    "b8e8baff",
                    "b7e7b9ff",
                    "b6e7b7ff",
                    "b5e6b6ff",
                    "b4e6b4ff",
                    "b4e5b3ff",
                    "b3e5b1ff",
                    "b2e5afff",
                    "b1e4aeff",
                    "b0e4acff",
                    "b0e3aaff",
                    "afe3a8ff",
                    "aee2a6ff",
                    "ade1a4ff",
                    "ade1a2ff",
                    "ace0a0ff",
                    "abdf9dff",
                    "aadf9bff",
                    "aade99ff",
                    "a9dd97ff",
                    "a9dc95ff",
                    "a8dc92ff",
                    "a8db90ff",
                    "a7da8eff",
                    "a7d98bff",
                    "a6d889ff",
                    "a6d787ff",
                    "a6d684ff",
                    "a6d582ff",
                    "a5d480ff",
                    "a5d37eff",
                    "a5d27cff",
                    "a6d17aff",
                    "a6d078ff",
                    "a6cf76ff",
                    "a6cd74ff",
                    "a6cc73ff",
                    "a6cb71ff",
                    "a6ca6fff",
                    "a7c96dff",
                    "a7c86cff",
                    "a7c66bff",
                    "a8c569ff",
                    "a8c368ff",
                    "a9c266ff",
                    "aac065ff",
                    "abbf64ff",
                    "acbd62ff",
                    "adbc61ff",
                    "afba5fff",
                    "b0b85eff",
                    "b2b75dff",
                    "b3b55cff",
                    "b5b35aff",
                    "b6b159ff",
                    "b8b058ff",
                    "b9ae57ff",
                    "bbac56ff",
                    "bdaa55ff",
                    "bea954ff",
                    "c0a753ff",
                    "c1a552ff",
                    "c3a351ff",
                    "c5a150ff",
                    "c79f4fff",
                    "c99d4eff",
                    "cb9b4dff",
                    "cc994cff",
                    "ce974cff",
                    "d0954bff",
                    "d1934aff",
                    "d39249ff",
                    "d49049ff",
                    "d68e48ff",
                    "d78d48ff",
                    "d88b47ff",
                    "da8947ff",
                    "db8846ff",
                    "dc8646ff",
                    "dd8446ff",
                    "dd8346ff",
                    "de8145ff",
                    "de7f46ff",
                    "df7d46ff",
                    "df7c45ff",
                    "df7a45ff",
                    "df7846ff",
                    "df7746ff",
                    "df7546ff",
                    "e07446ff",
                    "e07246ff",
                    "e07146ff",
                    "e06f47ff",
                    "e06e47ff",
                    "e06c47ff",
                    "e06b48ff",
                    "e06949ff",
                    "e16849ff",
                    "e1664aff",
                    "e1654bff",
                    "e1634cff",
                    "e1624cff",
                    "e1614dff",
                    "e15f4eff",
                    "e15e4eff",
                    "e25d4fff",
                    "e15b4fff",
                    "e15a50ff",
                    "e25850ff",
                    "e25750ff",
                    "e25651ff",
                    "e25451ff",
                    "e25351ff",
                    "e15150ff",
                    "e15050ff",
                    "e04f50ff",
                    "de4d50ff",
                    "dd4c4fff",
                    "db4a4eff",
                    "d8494eff",
                    "d6474dff",
                    "d4464cff",
                    "d1444bff",
                    "cf434aff",
                    "cc4149ff",
                    "c93f48ff",
                    "c63e47ff",
                    "c33c46ff",
                    "c03b45ff",
                    "bd3943ff",
                    "ba3842ff",
                    "b73641ff",
                    "b43540ff",
                    "b0343fff",
                    "ad323eff",
                    "aa313dff",
                    "a7303cff",
                    "a42e3bff",
                    "a12d39ff",
                    "9e2c38ff",
                    "9b2b38ff",
                    "992a37ff",
                    "962936ff",
                    "932835ff",
                    "912735ff",
                    "8e2635ff",
                    "8b2635ff",
                    "882534ff",
                    "842434ff",
                    "812334ff",
                    "7e2335ff",
                    "7b2334ff",
                    "782334ff",
                    "752235ff",
                    "722235ff",
                    "702235ff",
                    "6d2335ff",
                    "6a2335ff",
                    "682335ff",
                    "662335ff",
                    "642335ff",
                    "622336ff",
                    "602335ff",
                    "5e2436ff",
                    "3e0015ff"
                ],
                "type": "continuous",
                "title": "Methane at 400 hPa"
            }
        }
    ],
    "id": "AIRS_Methane_Volume_Mixing_Ratio_Daily_Night"
}