{
    "maps": [
        {
            "title": "Columnar Water Vapor",
            "type": "continuous",
            "legend": {
                "tooltips": [
                    "0.335 - 0.669",
                    "0.669 - 1.004",
                    "1.004 - 1.339",
                    "1.339 - 1.674",
                    "1.674 - 2.008",
                    "2.008 - 2.343",
                    "2.343 - 2.678",
                    "2.678 - 3.013",
                    "3.013 - 3.347",
                    "3.347 - 3.682",
                    "3.682 - 4.017",
                    "4.017 - 4.351",
                    "4.351 - 4.686",
                    "4.686 - 5.021",
                    "5.021 - 5.356",
                    "5.356 - 5.69",
                    "5.69 - 6.025",
                    "6.025 - 6.36",
                    "6.36 - 6.695",
                    "6.695 - 7.029",
                    "7.029 - 7.364",
                    "7.364 - 7.699",
                    "7.699 - 8.033",
                    "8.033 - 8.368",
                    "8.368 - 8.703",
                    "8.703 - 9.038",
                    "9.038 - 9.372",
                    "9.372 - 9.707",
                    "9.707 - 10.042",
                    "10.042 - 10.377",
                    "10.377 - 10.711",
                    "10.711 - 11.046",
                    "11.046 - 11.381",
                    "11.381 - 11.715",
                    "11.715 - 12.05",
                    "12.05 - 12.385",
                    "12.385 - 12.72",
                    "12.72 - 13.054",
                    "13.054 - 13.389",
                    "13.389 - 13.724",
                    "13.724 - 14.059",
                    "14.059 - 14.393",
                    "14.393 - 14.728",
                    "14.728 - 15.063",
                    "15.063 - 15.397",
                    "15.397 - 15.732",
                    "15.732 - 16.067",
                    "16.067 - 16.402",
                    "16.402 - 16.736",
                    "16.736 - 17.071",
                    "17.071 - 17.406",
                    "17.406 - 17.741",
                    "17.741 - 18.075",
                    "18.075 - 18.41",
                    "18.41 - 18.745",
                    "18.745 - 19.079",
                    "19.079 - 19.414",
                    "19.414 - 19.749",
                    "19.749 - 20.084",
                    "20.084 - 20.418",
                    "20.418 - 20.753",
                    "20.753 - 21.088",
                    "21.088 - 21.423",
                    "21.423 - 21.757",
                    "21.757 - 22.092",
                    "22.092 - 22.427",
                    "22.427 - 22.762",
                    "22.762 - 23.096",
                    "23.096 - 23.431",
                    "23.431 - 23.766",
                    "23.766 - 24.1",
                    "24.1 - 24.435",
                    "24.435 - 24.77",
                    "24.77 - 25.105",
                    "25.105 - 25.439",
                    "25.439 - 25.774",
                    "25.774 - 26.109",
                    "26.109 - 26.444",
                    "26.444 - 26.778",
                    "26.778 - 27.113",
                    "27.113 - 27.448",
                    "27.448 - 27.782",
                    "27.782 - 28.117",
                    "28.117 - 28.452",
                    "28.452 - 28.787",
                    "28.787 - 29.121",
                    "29.121 - 29.456",
                    "29.456 - 29.791",
                    "29.791 - 30.126",
                    "30.126 - 30.46",
                    "30.46 - 30.795",
                    "30.795 - 31.13",
                    "31.13 - 31.464",
                    "31.464 - 31.799",
                    "31.799 - 32.134",
                    "32.134 - 32.469",
                    "32.469 - 32.803",
                    "32.803 - 33.138",
                    "33.138 - 33.473",
                    "33.473 - 33.808",
                    "33.808 - 34.142",
                    "34.142 - 34.477",
                    "34.477 - 34.812",
                    "34.812 - 35.146",
                    "35.146 - 35.481",
                    "35.481 - 35.816",
                    "35.816 - 36.151",
                    "36.151 - 36.485",
                    "36.485 - 36.82",
                    "36.82 - 37.155",
                    "37.155 - 37.49",
                    "37.49 - 37.824",
                    "37.824 - 38.159",
                    "38.159 - 38.494",
                    "38.494 - 38.828",
                    "38.828 - 39.163",
                    "39.163 - 39.498",
                    "39.498 - 39.833",
                    "39.833 - 40.167",
                    "40.167 - 40.502",
                    "40.502 - 40.837",
                    "40.837 - 41.172",
                    "41.172 - 41.506",
                    "41.506 - 41.841",
                    "41.841 - 42.176",
                    "42.176 - 42.51",
                    "42.51 - 42.845",
                    "42.845 - 43.18",
                    "43.18 - 43.515",
                    "43.515 - 43.849",
                    "43.849 - 44.184",
                    "44.184 - 44.519",
                    "44.519 - 44.854",
                    "44.854 - 45.188",
                    "45.188 - 45.523",
                    "45.523 - 45.858",
                    "45.858 - 46.192",
                    "46.192 - 46.527",
                    "46.527 - 46.862",
                    "46.862 - 47.197",
                    "47.197 - 47.531",
                    "47.531 - 47.866",
                    "47.866 - 48.201",
                    "48.201 - 48.536",
                    "48.536 - 48.87",
                    "48.87 - 49.205",
                    "49.205 - 49.54",
                    "49.54 - 49.874",
                    "49.874 - 50.209",
                    "50.209 - 50.544",
                    "50.544 - 50.879",
                    "50.879 - 51.213",
                    "51.213 - 51.548",
                    "51.548 - 51.883",
                    "51.883 - 52.218",
                    "52.218 - 52.552",
                    "52.552 - 52.887",
                    "52.887 - 53.222",
                    "53.222 - 53.556",
                    "53.556 - 53.891",
                    "53.891 - 54.226",
                    "54.226 - 54.561",
                    "54.561 - 54.895",
                    "54.895 - 55.23",
                    "55.23 - 55.565",
                    "55.565 - 55.9",
                    "55.9 - 56.234",
                    "56.234 - 56.569",
                    "56.569 - 56.904",
                    "56.904 - 57.238",
                    "57.238 - 57.573",
                    "57.573 - 57.908",
                    "57.908 - 58.243",
                    "58.243 - 58.577",
                    "58.577 - 58.912",
                    "58.912 - 59.247",
                    "59.247 - 59.582",
                    "59.582 - 59.916",
                    "59.916 - 60.251",
                    "60.251 - 60.586",
                    "60.586 - 60.921",
                    "60.921 - 61.255",
                    "61.255 - 61.59",
                    "61.59 - 61.925",
                    "61.925 - 62.259",
                    "62.259 - 62.594",
                    "62.594 - 62.929",
                    "62.929 - 63.264",
                    "63.264 - 63.598",
                    "63.598 - 63.933",
                    "63.933 - 64.268",
                    "64.268 - 64.603",
                    "64.603 - 64.937",
                    "64.937 - 65.272",
                    "65.272 - 65.607",
                    "65.607 - 65.941",
                    "65.941 - 66.276",
                    "66.276 - 66.611",
                    "66.611 - 66.946",
                    "66.946 - 67.28",
                    "67.28 - 67.615",
                    "67.615 - 67.95",
                    "67.95 - 68.285",
                    "68.285 - 68.619",
                    "68.619 - 68.954",
                    "68.954 - 69.289",
                    "69.289 - 69.623",
                    "69.623 - 69.958",
                    "69.958 - 70.293",
                    "70.293 - 70.628",
                    "70.628 - 70.962",
                    "70.962 - 71.297",
                    "71.297 - 71.632",
                    "71.632 - 71.967",
                    "71.967 - 72.301",
                    "72.301 - 72.636",
                    "72.636 - 72.971",
                    "72.971 - 73.305",
                    "73.305 - 73.64",
                    "73.64 - 73.975",
                    "73.975 - 74.31",
                    "74.31 - 74.644",
                    "74.644 - 74.979",
                    "74.979 - 75.314",
                    "75.314 - 75.649",
                    "75.649 - 75.983",
                    "75.983 - 76.318",
                    "76.318 - 76.653",
                    "76.653 - 76.987",
                    "76.987 - 77.322",
                    "77.322 - 77.657",
                    "77.657 - 77.992",
                    "77.992 - 78.326",
                    "78.326 - 78.661",
                    "78.661 - 78.996",
                    "78.996 - 79.331",
                    "79.331 - 79.665",
                    "79.665 - 80.000",
                    "80.000"
                ],
                "title": "Columnar Water Vapor",
                "colors": [
                    "070007ff",
                    "0e000eff",
                    "150015ff",
                    "1c001cff",
                    "230023ff",
                    "2b002bff",
                    "320032ff",
                    "390039ff",
                    "400040ff",
                    "470047ff",
                    "4e004eff",
                    "550055ff",
                    "5c005cff",
                    "630063ff",
                    "6a006aff",
                    "710071ff",
                    "780078ff",
                    "800080ff",
                    "870087ff",
                    "8e008eff",
                    "950095ff",
                    "9c009cff",
                    "a300a3ff",
                    "aa00aaff",
                    "b100b1ff",
                    "b800b8ff",
                    "bf00bfff",
                    "c600c6ff",
                    "cd00cdff",
                    "d500d5ff",
                    "dc00dcff",
                    "e300e3ff",
                    "ea00eaff",
                    "f100f1ff",
                    "f800f8ff",
                    "ff00ffff",
                    "f800ffff",
                    "f100ffff",
                    "ea00ffff",
                    "e300ffff",
                    "dc00ffff",
                    "d400ffff",
                    "cd00ffff",
                    "c600ffff",
                    "bf00ffff",
                    "b800ffff",
                    "b100ffff",
                    "aa00ffff",
                    "a300ffff",
                    "9c00ffff",
                    "9500ffff",
                    "8e00ffff",
                    "8700ffff",
                    "7f00ffff",
                    "7800ffff",
                    "7100ffff",
                    "6a00ffff",
                    "6300ffff",
                    "5c00ffff",
                    "5500ffff",
                    "4e00ffff",
                    "4700ffff",
                    "4000ffff",
                    "3900ffff",
                    "3200ffff",
                    "2a00ffff",
                    "2300ffff",
                    "1c00ffff",
                    "1500ffff",
                    "0e00ffff",
                    "0700ffff",
                    "0000ffff",
                    "0008ffff",
                    "000fffff",
                    "0017ffff",
                    "001fffff",
                    "0027ffff",
                    "002effff",
                    "0036ffff",
                    "003effff",
                    "0046ffff",
                    "004dffff",
                    "0055ffff",
                    "005dffff",
                    "0064ffff",
                    "006cffff",
                    "0074ffff",
                    "007cffff",
                    "0083ffff",
                    "008bffff",
                    "0093ffff",
                    "009bffff",
                    "00a2ffff",
                    "00aaffff",
                    "00b2ffff",
                    "00b9ffff",
                    "00c1ffff",
                    "00c9ffff",
                    "00d1ffff",
                    "00d8ffff",
                    "00e0ffff",
                    "00e8ffff",
                    "00f0ffff",
                    "00f7ffff",
                    "00ffffff",
                    "00fcf7ff",
                    "00faf0ff",
                    "00f7e8ff",
                    "00f5e0ff",
                    "00f2d8ff",
                    "00f0d1ff",
                    "00edc9ff",
                    "00eac1ff",
                    "00e8b9ff",
                    "00e5b2ff",
                    "00e3aaff",
                    "00e0a2ff",
                    "00de9bff",
                    "00db93ff",
                    "00d88bff",
                    "00d683ff",
                    "00d37cff",
                    "00d174ff",
                    "00ce6cff",
                    "00cb64ff",
                    "00c95dff",
                    "00c655ff",
                    "00c44dff",
                    "00c146ff",
                    "00bf3eff",
                    "00bc36ff",
                    "00b92eff",
                    "00b727ff",
                    "00b41fff",
                    "00b217ff",
                    "00af0fff",
                    "00ad08ff",
                    "00aa00ff",
                    "07ac00ff",
                    "0eaf00ff",
                    "15b100ff",
                    "1cb300ff",
                    "23b600ff",
                    "2bb800ff",
                    "32bb00ff",
                    "39bd00ff",
                    "40bf00ff",
                    "47c200ff",
                    "4ec400ff",
                    "55c600ff",
                    "5cc900ff",
                    "63cb00ff",
                    "6acd00ff",
                    "71d000ff",
                    "78d200ff",
                    "80d500ff",
                    "87d700ff",
                    "8ed900ff",
                    "95dc00ff",
                    "9cde00ff",
                    "a3e000ff",
                    "aae300ff",
                    "b1e500ff",
                    "b8e700ff",
                    "bfea00ff",
                    "c6ec00ff",
                    "cdee00ff",
                    "d5f100ff",
                    "dcf300ff",
                    "e3f600ff",
                    "eaf800ff",
                    "f1fa00ff",
                    "f8fd00ff",
                    "ffff00ff",
                    "fff800ff",
                    "fff100ff",
                    "ffea00ff",
                    "ffe300ff",
                    "ffdc00ff",
                    "ffd400ff",
                    "ffcd00ff",
                    "ffc600ff",
                    "ffbf00ff",
                    "ffb800ff",
                    "ffb100ff",
                    "ffaa00ff",
                    "ffa300ff",
                    "ff9c00ff",
                    "ff9500ff",
                    "ff8e00ff",
                    "ff8700ff",
                    "ff7f00ff",
                    "ff7800ff",
                    "ff7100ff",
                    "ff6a00ff",
                    "ff6300ff",
                    "ff5c00ff",
                    "ff5500ff",
                    "ff4e00ff",
                    "ff4700ff",
                    "ff4000ff",
                    "ff3900ff",
                    "ff3200ff",
                    "ff2a00ff",
                    "ff2300ff",
                    "ff1c00ff",
                    "ff1500ff",
                    "ff0e00ff",
                    "ff0700ff",
                    "ff0000ff",
                    "ff0909ff",
                    "ff1212ff",
                    "ff1a1aff",
                    "ff2323ff",
                    "ff2c2cff",
                    "ff3535ff",
                    "ff3e3eff",
                    "ff4646ff",
                    "ff4f4fff",
                    "ff5858ff",
                    "ff6161ff",
                    "ff6a6aff",
                    "ff7272ff",
                    "ff7b7bff",
                    "ff8484ff",
                    "ff8d8dff",
                    "ff9595ff",
                    "ff9e9eff",
                    "ffa7a7ff",
                    "ffb0b0ff",
                    "ffb9b9ff",
                    "ffc1c1ff",
                    "ffcacaff",
                    "ffd3d3ff",
                    "ffdcdcff",
                    "ffe5e5ff",
                    "ffededff",
                    "fff6f6ff",
                    "ffffffff"
                ],
                "maxLabel": "80.000",
                "minLabel": "0.000",
                "units": "mm",
                "type": "continuous",
                "id": "AMSR2_Columnar_Water_Vapor_Night_0_legend"
            },
            "entries": {
                "values": [
                    [
                        0.334728,
                        0.669456
                    ],
                    [
                        0.669456,
                        1.004184
                    ],
                    [
                        1.004184,
                        1.338912
                    ],
                    [
                        1.338912,
                        1.67364
                    ],
                    [
                        1.67364,
                        2.008368
                    ],
                    [
                        2.008368,
                        2.343096
                    ],
                    [
                        2.343096,
                        2.677824
                    ],
                    [
                        2.677824,
                        3.012552
                    ],
                    [
                        3.012552,
                        3.34728
                    ],
                    [
                        3.34728,
                        3.682008
                    ],
                    [
                        3.682008,
                        4.016737
                    ],
                    [
                        4.016737,
                        4.351464
                    ],
                    [
                        4.351464,
                        4.686193
                    ],
                    [
                        4.686193,
                        5.02092
                    ],
                    [
                        5.02092,
                        5.355649
                    ],
                    [
                        5.355649,
                        5.690377
                    ],
                    [
                        5.690377,
                        6.025105
                    ],
                    [
                        6.025105,
                        6.359833
                    ],
                    [
                        6.359833,
                        6.694561
                    ],
                    [
                        6.694561,
                        7.029289
                    ],
                    [
                        7.029289,
                        7.364017
                    ],
                    [
                        7.364017,
                        7.698745
                    ],
                    [
                        7.698745,
                        8.033473
                    ],
                    [
                        8.033473,
                        8.368201
                    ],
                    [
                        8.368201,
                        8.702929
                    ],
                    [
                        8.702929,
                        9.037657
                    ],
                    [
                        9.037657,
                        9.372385
                    ],
                    [
                        9.372385,
                        9.707113
                    ],
                    [
                        9.707113,
                        10.041841
                    ],
                    [
                        10.041841,
                        10.376569
                    ],
                    [
                        10.376569,
                        10.711297
                    ],
                    [
                        10.711297,
                        11.046025
                    ],
                    [
                        11.046025,
                        11.380754
                    ],
                    [
                        11.380754,
                        11.715481
                    ],
                    [
                        11.715481,
                        12.050209
                    ],
                    [
                        12.050209,
                        12.384937
                    ],
                    [
                        12.384937,
                        12.719666
                    ],
                    [
                        12.719666,
                        13.054393
                    ],
                    [
                        13.054393,
                        13.389121
                    ],
                    [
                        13.389121,
                        13.723849
                    ],
                    [
                        13.723849,
                        14.058578
                    ],
                    [
                        14.058578,
                        14.393306
                    ],
                    [
                        14.393306,
                        14.728033
                    ],
                    [
                        14.728033,
                        15.062761
                    ],
                    [
                        15.062761,
                        15.39749
                    ],
                    [
                        15.39749,
                        15.732218
                    ],
                    [
                        15.732218,
                        16.066946
                    ],
                    [
                        16.066946,
                        16.401674
                    ],
                    [
                        16.401674,
                        16.736403
                    ],
                    [
                        16.736403,
                        17.071129
                    ],
                    [
                        17.071129,
                        17.405857
                    ],
                    [
                        17.405857,
                        17.740585
                    ],
                    [
                        17.740585,
                        18.075314
                    ],
                    [
                        18.075314,
                        18.410042
                    ],
                    [
                        18.410042,
                        18.74477
                    ],
                    [
                        18.74477,
                        19.079498
                    ],
                    [
                        19.079498,
                        19.414227
                    ],
                    [
                        19.414227,
                        19.748955
                    ],
                    [
                        19.748955,
                        20.083681
                    ],
                    [
                        20.083681,
                        20.418409
                    ],
                    [
                        20.418409,
                        20.753138
                    ],
                    [
                        20.753138,
                        21.087866
                    ],
                    [
                        21.087866,
                        21.422594
                    ],
                    [
                        21.422594,
                        21.757322
                    ],
                    [
                        21.757322,
                        22.092051
                    ],
                    [
                        22.092051,
                        22.426779
                    ],
                    [
                        22.426779,
                        22.761507
                    ],
                    [
                        22.761507,
                        23.096233
                    ],
                    [
                        23.096233,
                        23.430962
                    ],
                    [
                        23.430962,
                        23.76569
                    ],
                    [
                        23.76569,
                        24.100418
                    ],
                    [
                        24.100418,
                        24.435146
                    ],
                    [
                        24.435146,
                        24.769875
                    ],
                    [
                        24.769875,
                        25.104603
                    ],
                    [
                        25.104603,
                        25.439331
                    ],
                    [
                        25.439331,
                        25.774059
                    ],
                    [
                        25.774059,
                        26.108786
                    ],
                    [
                        26.108786,
                        26.443514
                    ],
                    [
                        26.443514,
                        26.778242
                    ],
                    [
                        26.778242,
                        27.11297
                    ],
                    [
                        27.11297,
                        27.447699
                    ],
                    [
                        27.447699,
                        27.782427
                    ],
                    [
                        27.782427,
                        28.117155
                    ],
                    [
                        28.117155,
                        28.451883
                    ],
                    [
                        28.451883,
                        28.786612
                    ],
                    [
                        28.786612,
                        29.121338
                    ],
                    [
                        29.121338,
                        29.456066
                    ],
                    [
                        29.456066,
                        29.790794
                    ],
                    [
                        29.790794,
                        30.125523
                    ],
                    [
                        30.125523,
                        30.460251
                    ],
                    [
                        30.460251,
                        30.794979
                    ],
                    [
                        30.794979,
                        31.129707
                    ],
                    [
                        31.129707,
                        31.464436
                    ],
                    [
                        31.464436,
                        31.799164
                    ],
                    [
                        31.799164,
                        32.133892
                    ],
                    [
                        32.133892,
                        32.46862
                    ],
                    [
                        32.46862,
                        32.803349
                    ],
                    [
                        32.803349,
                        33.138077
                    ],
                    [
                        33.138077,
                        33.472805
                    ],
                    [
                        33.472805,
                        33.807529
                    ],
                    [
                        33.807529,
                        34.142258
                    ],
                    [
                        34.142258,
                        34.476986
                    ],
                    [
                        34.476986,
                        34.811714
                    ],
                    [
                        34.811714,
                        35.146442
                    ],
                    [
                        35.146442,
                        35.481171
                    ],
                    [
                        35.481171,
                        35.815899
                    ],
                    [
                        35.815899,
                        36.150627
                    ],
                    [
                        36.150627,
                        36.485355
                    ],
                    [
                        36.485355,
                        36.820084
                    ],
                    [
                        36.820084,
                        37.154812
                    ],
                    [
                        37.154812,
                        37.48954
                    ],
                    [
                        37.48954,
                        37.824268
                    ],
                    [
                        37.824268,
                        38.158997
                    ],
                    [
                        38.158997,
                        38.493725
                    ],
                    [
                        38.493725,
                        38.828453
                    ],
                    [
                        38.828453,
                        39.163181
                    ],
                    [
                        39.163181,
                        39.49791
                    ],
                    [
                        39.49791,
                        39.832634
                    ],
                    [
                        39.832634,
                        40.167362
                    ],
                    [
                        40.167362,
                        40.50209
                    ],
                    [
                        40.50209,
                        40.836819
                    ],
                    [
                        40.836819,
                        41.171547
                    ],
                    [
                        41.171547,
                        41.506275
                    ],
                    [
                        41.506275,
                        41.841003
                    ],
                    [
                        41.841003,
                        42.175732
                    ],
                    [
                        42.175732,
                        42.51046
                    ],
                    [
                        42.51046,
                        42.845188
                    ],
                    [
                        42.845188,
                        43.179916
                    ],
                    [
                        43.179916,
                        43.514645
                    ],
                    [
                        43.514645,
                        43.849373
                    ],
                    [
                        43.849373,
                        44.184101
                    ],
                    [
                        44.184101,
                        44.518829
                    ],
                    [
                        44.518829,
                        44.853558
                    ],
                    [
                        44.853558,
                        45.188286
                    ],
                    [
                        45.188286,
                        45.523014
                    ],
                    [
                        45.523014,
                        45.857742
                    ],
                    [
                        45.857742,
                        46.192467
                    ],
                    [
                        46.192467,
                        46.527195
                    ],
                    [
                        46.527195,
                        46.861923
                    ],
                    [
                        46.861923,
                        47.196651
                    ],
                    [
                        47.196651,
                        47.53138
                    ],
                    [
                        47.53138,
                        47.866108
                    ],
                    [
                        47.866108,
                        48.200836
                    ],
                    [
                        48.200836,
                        48.535564
                    ],
                    [
                        48.535564,
                        48.870293
                    ],
                    [
                        48.870293,
                        49.205021
                    ],
                    [
                        49.205021,
                        49.539749
                    ],
                    [
                        49.539749,
                        49.874477
                    ],
                    [
                        49.874477,
                        50.209206
                    ],
                    [
                        50.209206,
                        50.543934
                    ],
                    [
                        50.543934,
                        50.878662
                    ],
                    [
                        50.878662,
                        51.21339
                    ],
                    [
                        51.21339,
                        51.548119
                    ],
                    [
                        51.548119,
                        51.882847
                    ],
                    [
                        51.882847,
                        52.217571
                    ],
                    [
                        52.217571,
                        52.552299
                    ],
                    [
                        52.552299,
                        52.887028
                    ],
                    [
                        52.887028,
                        53.221756
                    ],
                    [
                        53.221756,
                        53.556484
                    ],
                    [
                        53.556484,
                        53.891212
                    ],
                    [
                        53.891212,
                        54.225941
                    ],
                    [
                        54.225941,
                        54.560669
                    ],
                    [
                        54.560669,
                        54.895397
                    ],
                    [
                        54.895397,
                        55.230125
                    ],
                    [
                        55.230125,
                        55.564854
                    ],
                    [
                        55.564854,
                        55.899582
                    ],
                    [
                        55.899582,
                        56.23431
                    ],
                    [
                        56.23431,
                        56.569038
                    ],
                    [
                        56.569038,
                        56.903767
                    ],
                    [
                        56.903767,
                        57.238495
                    ],
                    [
                        57.238495,
                        57.573223
                    ],
                    [
                        57.573223,
                        57.907951
                    ],
                    [
                        57.907951,
                        58.242676
                    ],
                    [
                        58.242676,
                        58.577404
                    ],
                    [
                        58.577404,
                        58.912132
                    ],
                    [
                        58.912132,
                        59.246861
                    ],
                    [
                        59.246861,
                        59.581589
                    ],
                    [
                        59.581589,
                        59.916317
                    ],
                    [
                        59.916317,
                        60.251045
                    ],
                    [
                        60.251045,
                        60.585773
                    ],
                    [
                        60.585773,
                        60.920502
                    ],
                    [
                        60.920502,
                        61.25523
                    ],
                    [
                        61.25523,
                        61.589958
                    ],
                    [
                        61.589958,
                        61.924686
                    ],
                    [
                        61.924686,
                        62.259415
                    ],
                    [
                        62.259415,
                        62.594143
                    ],
                    [
                        62.594143,
                        62.928871
                    ],
                    [
                        62.928871,
                        63.263599
                    ],
                    [
                        63.263599,
                        63.598328
                    ],
                    [
                        63.598328,
                        63.933056
                    ],
                    [
                        63.933056,
                        64.267784
                    ],
                    [
                        64.267784,
                        64.602509
                    ],
                    [
                        64.602509,
                        64.937241
                    ],
                    [
                        64.937241,
                        65.271965
                    ],
                    [
                        65.271965,
                        65.606697
                    ],
                    [
                        65.606697,
                        65.941422
                    ],
                    [
                        65.941422,
                        66.276154
                    ],
                    [
                        66.276154,
                        66.610878
                    ],
                    [
                        66.610878,
                        66.94561
                    ],
                    [
                        66.94561,
                        67.280334
                    ],
                    [
                        67.280334,
                        67.615059
                    ],
                    [
                        67.615059,
                        67.949791
                    ],
                    [
                        67.949791,
                        68.284515
                    ],
                    [
                        68.284515,
                        68.619247
                    ],
                    [
                        68.619247,
                        68.953972
                    ],
                    [
                        68.953972,
                        69.288704
                    ],
                    [
                        69.288704,
                        69.623428
                    ],
                    [
                        69.623428,
                        69.95816
                    ],
                    [
                        69.95816,
                        70.292885
                    ],
                    [
                        70.292885,
                        70.627617
                    ],
                    [
                        70.627617,
                        70.962341
                    ],
                    [
                        70.962341,
                        71.297073
                    ],
                    [
                        71.297073,
                        71.631798
                    ],
                    [
                        71.631798,
                        71.96653
                    ],
                    [
                        71.96653,
                        72.301254
                    ],
                    [
                        72.301254,
                        72.635986
                    ],
                    [
                        72.635986,
                        72.970711
                    ],
                    [
                        72.970711,
                        73.305443
                    ],
                    [
                        73.305443,
                        73.640167
                    ],
                    [
                        73.640167,
                        73.974892
                    ],
                    [
                        73.974892,
                        74.309624
                    ],
                    [
                        74.309624,
                        74.644348
                    ],
                    [
                        74.644348,
                        74.97908
                    ],
                    [
                        74.97908,
                        75.313805
                    ],
                    [
                        75.313805,
                        75.648537
                    ],
                    [
                        75.648537,
                        75.983261
                    ],
                    [
                        75.983261,
                        76.317993
                    ],
                    [
                        76.317993,
                        76.652718
                    ],
                    [
                        76.652718,
                        76.98745
                    ],
                    [
                        76.98745,
                        77.322174
                    ],
                    [
                        77.322174,
                        77.656906
                    ],
                    [
                        77.656906,
                        77.991631
                    ],
                    [
                        77.991631,
                        78.326363
                    ],
                    [
                        78.326363,
                        78.661087
                    ],
                    [
                        78.661087,
                        78.995819
                    ],
                    [
                        78.995819,
                        79.330544
                    ],
                    [
                        79.330544,
                        79.665268
                    ],
                    [
                        79.665268,
                        80.0
                    ],
                    [
                        80.0
                    ]
                ],
                "colors": [
                    "070007ff",
                    "0e000eff",
                    "150015ff",
                    "1c001cff",
                    "230023ff",
                    "2b002bff",
                    "320032ff",
                    "390039ff",
                    "400040ff",
                    "470047ff",
                    "4e004eff",
                    "550055ff",
                    "5c005cff",
                    "630063ff",
                    "6a006aff",
                    "710071ff",
                    "780078ff",
                    "800080ff",
                    "870087ff",
                    "8e008eff",
                    "950095ff",
                    "9c009cff",
                    "a300a3ff",
                    "aa00aaff",
                    "b100b1ff",
                    "b800b8ff",
                    "bf00bfff",
                    "c600c6ff",
                    "cd00cdff",
                    "d500d5ff",
                    "dc00dcff",
                    "e300e3ff",
                    "ea00eaff",
                    "f100f1ff",
                    "f800f8ff",
                    "ff00ffff",
                    "f800ffff",
                    "f100ffff",
                    "ea00ffff",
                    "e300ffff",
                    "dc00ffff",
                    "d400ffff",
                    "cd00ffff",
                    "c600ffff",
                    "bf00ffff",
                    "b800ffff",
                    "b100ffff",
                    "aa00ffff",
                    "a300ffff",
                    "9c00ffff",
                    "9500ffff",
                    "8e00ffff",
                    "8700ffff",
                    "7f00ffff",
                    "7800ffff",
                    "7100ffff",
                    "6a00ffff",
                    "6300ffff",
                    "5c00ffff",
                    "5500ffff",
                    "4e00ffff",
                    "4700ffff",
                    "4000ffff",
                    "3900ffff",
                    "3200ffff",
                    "2a00ffff",
                    "2300ffff",
                    "1c00ffff",
                    "1500ffff",
                    "0e00ffff",
                    "0700ffff",
                    "0000ffff",
                    "0008ffff",
                    "000fffff",
                    "0017ffff",
                    "001fffff",
                    "0027ffff",
                    "002effff",
                    "0036ffff",
                    "003effff",
                    "0046ffff",
                    "004dffff",
                    "0055ffff",
                    "005dffff",
                    "0064ffff",
                    "006cffff",
                    "0074ffff",
                    "007cffff",
                    "0083ffff",
                    "008bffff",
                    "0093ffff",
                    "009bffff",
                    "00a2ffff",
                    "00aaffff",
                    "00b2ffff",
                    "00b9ffff",
                    "00c1ffff",
                    "00c9ffff",
                    "00d1ffff",
                    "00d8ffff",
                    "00e0ffff",
                    "00e8ffff",
                    "00f0ffff",
                    "00f7ffff",
                    "00ffffff",
                    "00fcf7ff",
                    "00faf0ff",
                    "00f7e8ff",
                    "00f5e0ff",
                    "00f2d8ff",
                    "00f0d1ff",
                    "00edc9ff",
                    "00eac1ff",
                    "00e8b9ff",
                    "00e5b2ff",
                    "00e3aaff",
                    "00e0a2ff",
                    "00de9bff",
                    "00db93ff",
                    "00d88bff",
                    "00d683ff",
                    "00d37cff",
                    "00d174ff",
                    "00ce6cff",
                    "00cb64ff",
                    "00c95dff",
                    "00c655ff",
                    "00c44dff",
                    "00c146ff",
                    "00bf3eff",
                    "00bc36ff",
                    "00b92eff",
                    "00b727ff",
                    "00b41fff",
                    "00b217ff",
                    "00af0fff",
                    "00ad08ff",
                    "00aa00ff",
                    "07ac00ff",
                    "0eaf00ff",
                    "15b100ff",
                    "1cb300ff",
                    "23b600ff",
                    "2bb800ff",
                    "32bb00ff",
                    "39bd00ff",
                    "40bf00ff",
                    "47c200ff",
                    "4ec400ff",
                    "55c600ff",
                    "5cc900ff",
                    "63cb00ff",
                    "6acd00ff",
                    "71d000ff",
                    "78d200ff",
                    "80d500ff",
                    "87d700ff",
                    "8ed900ff",
                    "95dc00ff",
                    "9cde00ff",
                    "a3e000ff",
                    "aae300ff",
                    "b1e500ff",
                    "b8e700ff",
                    "bfea00ff",
                    "c6ec00ff",
                    "cdee00ff",
                    "d5f100ff",
                    "dcf300ff",
                    "e3f600ff",
                    "eaf800ff",
                    "f1fa00ff",
                    "f8fd00ff",
                    "ffff00ff",
                    "fff800ff",
                    "fff100ff",
                    "ffea00ff",
                    "ffe300ff",
                    "ffdc00ff",
                    "ffd400ff",
                    "ffcd00ff",
                    "ffc600ff",
                    "ffbf00ff",
                    "ffb800ff",
                    "ffb100ff",
                    "ffaa00ff",
                    "ffa300ff",
                    "ff9c00ff",
                    "ff9500ff",
                    "ff8e00ff",
                    "ff8700ff",
                    "ff7f00ff",
                    "ff7800ff",
                    "ff7100ff",
                    "ff6a00ff",
                    "ff6300ff",
                    "ff5c00ff",
                    "ff5500ff",
                    "ff4e00ff",
                    "ff4700ff",
                    "ff4000ff",
                    "ff3900ff",
                    "ff3200ff",
                    "ff2a00ff",
                    "ff2300ff",
                    "ff1c00ff",
                    "ff1500ff",
                    "ff0e00ff",
                    "ff0700ff",
                    "ff0000ff",
                    "ff0909ff",
                    "ff1212ff",
                    "ff1a1aff",
                    "ff2323ff",
                    "ff2c2cff",
                    "ff3535ff",
                    "ff3e3eff",
                    "ff4646ff",
                    "ff4f4fff",
                    "ff5858ff",
                    "ff6161ff",
                    "ff6a6aff",
                    "ff7272ff",
                    "ff7b7bff",
                    "ff8484ff",
                    "ff8d8dff",
                    "ff9595ff",
                    "ff9e9eff",
                    "ffa7a7ff",
                    "ffb0b0ff",
                    "ffb9b9ff",
                    "ffc1c1ff",
                    "ffcacaff",
                    "ffd3d3ff",
                    "ffdcdcff",
                    "ffe5e5ff",
                    "ffededff",
                    "fff6f6ff",
                    "ffffffff"
                ],
                "type": "continuous",
                "title": "Columnar Water Vapor"
            }
        }
    ],
    "id": "AMSR2_Columnar_Water_Vapor_Night"
}